{
   "tokens": [
      {
         "string": "design pattern",
         "tag": "NN",
         "tokentag": "word"
      },
      {
         "string": "singleton",
         "tag": "NN",
         "tokentag": "word"
      },
      {
         "string": "factory",
         "tag": "NN",
         "tokentag": "word"
      },
      {
         "string": "bean",
         "tag": "NN",
         "tokentag": "word"
      },
      {
         "string": "prototype",
         "tag": "NN",
         "tokentag": "word"
      },
      {
         "string": "message passing",
         "tag": "NN",
         "tokentag": "word"
      },
      {
         "string": "class",
         "tag": "NN",
         "tokentag": "word"
      },
      {
         "string": "object oriented",
         "tag": "JJ",
         "tokentag": "word"
      },
      {
         "string": "generic",
         "tag": "JJ",
         "tokentag": "word"
      }
   ],
   "arrows": []
}